toolshelf/__init__.py
toolshelf/database.py
toolshelf/main.py
toolshelf/entry_points/__init__.py
toolshelf/entry_points/toolshelf_runner.py
toolshelf/exceptions/__init__.py
toolshelf/exceptions/invalid_tool_exception.py
toolshelf/managers/__init__.py
toolshelf/managers/tool_manager.py
toolshelf/models/__init__.py
toolshelf/models/tool_item.py
toolshelf/screens/__init__.py
toolshelf/screens/confirm_modal.py
toolshelf/screens/create_tool_modal.py
toolshelf/screens/edit_tool_modal.py
toolshelf/screens/tool_description.py
toolshelf/styling/create_tool_modal.tcss
toolshelf/styling/dock_sidebar.tcss
toolshelf/styling/tool_description.tcss
toolshelf/widgets/__init__.py
toolshelf/widgets/tool_description_desc_widget.py
toolshelf_ui-0.0.5.dist-info/METADATA
toolshelf_ui-0.0.5.dist-info/WHEEL
toolshelf_ui-0.0.5.dist-info/entry_points.txt
toolshelf_ui-0.0.5.dist-info/top_level.txt
toolshelf_ui-0.0.5.dist-info/RECORD
