Metadata-Version: 2.1
Name: toolshelf-ui
Version: 0.0.5
Summary: A versatile tool management utility for developers
Home-page: https://github.com/Atophite/toolshelf
Author: Atophite
Keywords: python,command-line,tool,TUI,Terminal User Interface
Classifier: Programming Language :: Python :: 3
Requires-Dist: textual
Requires-Dist: rich
Requires-Dist: sqlalchemy
Requires-Dist: pyperclip
